<?xml version="1.0" encoding="utf-8" ?>

<introContent>
	<extensionContent id="com.sap.adt.intro.abap.dev.tut"
		style="css/sample.css" name="ABAP DEVELOPMENT" path="tutorials/@">
			<group style-id="content-group" id="content-group" label="ABAP Development">
				<link
					url="http://org.eclipse.ui.intro/showStandby?partId=org.eclipse.platform.cheatsheet&amp;input=com.sap.adt.cheatsheet.create.abap.project"
					label="Create Your First ABAP Project" id="core_abapproject_exe"
					style-id="content-link">
					<text>The cheat sheet guides you interactively through all steps necessary to create your first ABAP project and handle system connection, even for different ABAP systems at the same time.</text>
				</link>

				<link
					url="http://org.eclipse.ui.intro/showStandby?partId=org.eclipse.platform.cheatsheet&amp;input=com.sap.adt.cheatsheet.add.abap.devobjects"
					label="Create ABAP Development Objects" id="core_abapproject_exe"
					style-id="content-link">
					<text>The cheat sheet shows you how to add new development objects to your ABAP project.</text>
				</link>

				<link
					url="http://org.eclipse.ui.intro/showStandby?partId=org.eclipse.platform.cheatsheet&amp;input=com.sap.adt.cheatsheet.search.abap.devobjects"
					label="Apply Global Search and Where-Used Function" id="core_abapsearch_exe"
					style-id="content-link">
					<text>This cheat sheet shows you how to carry out a system-wide search for any ABAP development object.</text>
				</link>

				<link
					url="http://org.eclipse.ui.intro/showStandby?partId=org.eclipse.platform.cheatsheet&amp;input=com.sap.adt.cheatsheet.abap.templates"
					label="Create Your Own ABAP Code Templates" id="core_abapstandard_exe"
					style-id="content-link">
					<text>This cheat sheet assists you when creating and using your own ABAP templates.</text>
				</link>
		</group>
	</extensionContent>
</introContent>